pyture_remo/__init__.py
pyture_remo/api.py
pyture_remo/appliance.py
pyture_remo/appliance_test.py
pyture_remo/button.py
pyture_remo/device.py
pyture_remo/light.py
pyture_remo/remo.py
pyture_remo/remo_test.py
pyture_remo/signal.py
pyture_remo/testdata/appliances.json
pyture_remo/testdata/devices.json
pyture_remo/tv.py
pyture_remo/user.py
pyture_remo-0.2.3.dist-info/LICENSE
pyture_remo-0.2.3.dist-info/WHEEL
pyture_remo-0.2.3.dist-info/METADATA
pyture_remo-0.2.3.dist-info/RECORD
