Metadata-Version: 2.1
Name: pyture-remo
Version: 0.2.3
Summary: nature-remo library for Python
License: MIT
Author: Suzuka Asagiri
Author-email: admin@suzutan.jp
Requires-Python: >=3.6,<4.0
Classifier: License :: OSI Approved :: MIT License
Classifier: Programming Language :: Python :: 3
Classifier: Programming Language :: Python :: 3.6
Classifier: Programming Language :: Python :: 3.7
Classifier: Programming Language :: Python :: 3.8
Requires-Dist: requests (>=2.23.0,<3.0.0)
